nwunity/__init__.py
nwunity/cli.py
nwunity/handlers.py
nwunity/data/escape.js
nwunity/data/game_launcher_template.sh
nwunity/data/jquery.min.js
nwunity/data/libffmpeg.so
nwunity/data/package.json
nwunity/data/style.css
nwunity/data/unity_logo.png
nwunity-0.2.22.dist-info/LICENSE
nwunity-0.2.22.dist-info/METADATA
nwunity-0.2.22.dist-info/WHEEL
nwunity-0.2.22.dist-info/entry_points.txt
nwunity-0.2.22.dist-info/top_level.txt
nwunity-0.2.22.dist-info/RECORD
