Metadata-Version: 2.1
Name: nwunity
Version: 0.2.22
Summary: NW-Unity is a tool for auto packing your Unity WebGL output folder to a NW.js executable folder.
Home-page: https://github.com/zzxzzk115/NW-Unity
Author: Lazy_V
Author-email: 954294627@qq.com
License: UNKNOWN
Keywords: NW.js,GameShell,Unity,WebGL
Platform: UNKNOWN
Requires-Python: >=3
